aws-nsm-interface/__init__.py
aws_nsm_interface/__init__.py
aws_nsm_interface/exceptions.py
aws_nsm_interface/structs.py
aws_nsm_interface-1.0.0.dist-info/LICENSE
aws_nsm_interface-1.0.0.dist-info/METADATA
aws_nsm_interface-1.0.0.dist-info/WHEEL
aws_nsm_interface-1.0.0.dist-info/top_level.txt
aws_nsm_interface-1.0.0.dist-info/RECORD
