Metadata-Version: 2.1
Name: aws-nsm-interface
Version: 1.0.0
Summary: Native Python interface for the AWS Nitro Secure Module (NSM)
Home-page: https://github.com/donkersgoed/aws-nsm-interface
Author: Luc van Donkersgoed
Author-email: lucvandonkersgoed+python@gmail.com
License: UNKNOWN
Platform: UNKNOWN
Classifier: Programming Language :: Python :: 3
Classifier: License :: OSI Approved :: MIT License
Classifier: Operating System :: OS Independent
Requires-Python: >=3.6
Requires-Dist: cbor2 (>=5.2.0)
Requires-Dist: ioctl-opt (>=1.2.2)
